gesetze/__init__.py
gesetze/cli/__init__.py
gesetze/cli/factory.py
gesetze/cli/scraper.py
gesetze/cli/scrapers/__init__.py
gesetze/cli/scrapers/buzer.py
gesetze/cli/scrapers/dejure.py
gesetze/cli/scrapers/gesetze.py
gesetze/cli/scrapers/lexparency.py
gesetze/gesetz.py
gesetze/library.py
gesetze/models/__init__.py
gesetze/models/norm.py
gesetze/nomoi.sqlite
gesetze/utils.py
gesetze-1.2.2.dist-info/entry_points.txt
gesetze-1.2.2.dist-info/LICENSE
gesetze-1.2.2.dist-info/WHEEL
gesetze-1.2.2.dist-info/METADATA
gesetze-1.2.2.dist-info/RECORD
