Metadata-Version: 2.1
Name: gesetze
Version: 1.2.2
Summary: Linking german legal norms, dependency-free & GDPR-friendly
Home-page: https://digitalbuero.eu
License: GPL-3.0-only
Keywords: buzer,cli,dejure,gesetze-im-internet,law,laws,legal,lexparency
Author: Digitalbüro
Author-email: post@digitalbuero.eu
Maintainer: Martin Folkers
Maintainer-email: hello@twobrain.io
Requires-Python: >=3.7,<4.0
Classifier: Development Status :: 5 - Production/Stable
Classifier: Environment :: Console
Classifier: Environment :: Web Environment
Classifier: Intended Audience :: Developers
Classifier: Intended Audience :: Legal Industry
Classifier: License :: OSI Approved :: GNU General Public License v3 (GPLv3)
Classifier: Operating System :: OS Independent
Classifier: Programming Language :: Python :: 3
Classifier: Programming Language :: Python :: 3.7
Classifier: Programming Language :: Python :: 3.8
Classifier: Programming Language :: Python :: 3.9
Classifier: Programming Language :: Python :: 3.10
Classifier: Programming Language :: Python :: 3.10
Classifier: Programming Language :: Python :: 3.11
Classifier: Programming Language :: Python :: 3.8
Classifier: Programming Language :: Python :: 3.9
Classifier: Programming Language :: SQL
Classifier: Topic :: Database
Classifier: Topic :: Internet :: WWW/HTTP
Classifier: Topic :: Software Development :: Libraries :: Python Modules
Classifier: Topic :: Text Processing :: Markup :: HTML
Classifier: Topic :: Text Processing :: Markup :: Markdown
Provides-Extra: cli
Requires-Dist: aiofiles (>=22,<23); extra == "cli"
Requires-Dist: aiohttp (>=3,<4); extra == "cli"
Requires-Dist: beautifulsoup4 (>=4,<5)
Requires-Dist: click (>=8,<9); extra == "cli"
Requires-Dist: lxml (>=4,<5); extra == "cli"
Project-URL: Funding, https://donate.rsf.org
Project-URL: Issue Tracker, https://codeberg.org/digitalbuero/py-gesetze/issues
Project-URL: Repository, https://codeberg.org/digitalbuero/py-gesetze
